tvopt/__init__.py
tvopt/costs.py
tvopt/distributed_solvers.py
tvopt/networks.py
tvopt/prediction.py
tvopt/sets.py
tvopt/solvers.py
tvopt/utils.py
tvopt-0.1.dist-info/LICENSE
tvopt-0.1.dist-info/METADATA
tvopt-0.1.dist-info/WHEEL
tvopt-0.1.dist-info/top_level.txt
tvopt-0.1.dist-info/RECORD
