Metadata-Version: 2.1
Name: tvopt
Version: 0.1
Summary: tvopt: A Python Framework for Time-Varying Optimization
Home-page: https://github.com/nicola-bastianello/tvopt
Author: Nicola Bastianello
Author-email: nicola.bastianello.3@phd.unipd.it
License: UNKNOWN
Platform: UNKNOWN
Classifier: Programming Language :: Python :: 3
Classifier: License :: OSI Approved :: GNU General Public License v3 (GPLv3)
Classifier: Operating System :: OS Independent
Requires-Python: >=3.6
Requires-Dist: numpy (>=1.19)
Requires-Dist: scipy (>=1.5)
